data/Annotation_data_human.txt
data/Annotation_data_mouse.txt
data/ReactomePathways.txt
data/ReactomePathwaysRelation.txt
data/UniProt2Reactome.txt
data/UniProt2Reactome_All_Levels.txt
mssuite/__init__.py
mssuite/mssuite.py
mssuite-1.8.dist-info/METADATA
mssuite-1.8.dist-info/WHEEL
mssuite-1.8.dist-info/top_level.txt
mssuite-1.8.dist-info/RECORD
